lmlibs-1.0.0.dist-info/RECORD
lmlibs-1.0.0.dist-info/WHEEL
lmlibs-1.0.0.dist-info/top_level.txt
lmlibs-1.0.0.dist-info/METADATA
lmplot/plots.cpython-312-darwin.so
lmroute/gis_router.cpython-312-darwin.so
