Metadata-Version: 2.4
Name: lmlibs
Version: 1.0.0
Summary: Optimized routing and plotting libraries
